[
    {
        "vehicle": "Bike",
        "rent" : "$38/h",
        "image": "https://imgd.aeplcdn.com/476x268/bw/ec/15278/Royal-Enfield-Classic-350-Side-87562.jpg?v=201711021421&q=70"
    },

    {
        "vehicle": "Car",
        "rent" : "$90/h",
        "image": "https://upload.wikimedia.org/wikipedia/commons/thumb/4/49/2013-2016_Toyota_Corolla_%28ZRE172R%29_SX_sedan_%282018-09-17%29_01.jpg/300px-2013-2016_Toyota_Corolla_%28ZRE172R%29_SX_sedan_%282018-09-17%29_01.jpg"
    },
    {
        "vehicle": "Bus",
        "rent" : "$58/h",
        "image": "https://etimg.etb2bimg.com/photo/71442867.cms"
    },
    {
        "vehicle": "Train",
        "rent" : "$46/h",
        "image": "https://ichef.bbci.co.uk/news/624/cpsprodpb/782C/production/_110046703_gettyimages-175800489.jpg"
    }
]